exemplar_based_inpainting/__init__.py
exemplar_based_inpainting/cli_app.py
exemplar_based_inpainting/image_utils.py
exemplar_based_inpainting/inpainter.py
exemplar_based_inpainting/simple_image_masker.py
tests/__init__.py
tests/test_exemplar_based_inpainting.py
exemplar_based_inpainting-0.2.0.dist-info/LICENSE
exemplar_based_inpainting-0.2.0.dist-info/METADATA
exemplar_based_inpainting-0.2.0.dist-info/WHEEL
exemplar_based_inpainting-0.2.0.dist-info/entry_points.txt
exemplar_based_inpainting-0.2.0.dist-info/top_level.txt
exemplar_based_inpainting-0.2.0.dist-info/RECORD
