Metadata-Version: 2.1
Name: exemplar-based-inpainting
Version: 0.2.0
Summary: Python implementation of the exemplar-based inpainting method of Criminisi et al.
Author-email: Ricard Campos <ricard.campos@coronis.es>
Classifier: Development Status :: 2 - Pre-Alpha
Classifier: Intended Audience :: Developers
Classifier: Programming Language :: Python :: 3
Classifier: Programming Language :: Python :: 3.6
Classifier: Programming Language :: Python :: 3.7
Classifier: Programming Language :: Python :: 3.8
Classifier: Operating System :: OS Independent
Classifier: Natural Language :: English
Requires-Python: >=3.7
License-File: LICENSE
Requires-Dist: flake8
Requires-Dist: mkdocs
Requires-Dist: mkdocstrings[python]
Requires-Dist: mkdocs-material
Requires-Dist: pymdown-extensions
Requires-Dist: mkdocs-include-markdown-plugin
Requires-Dist: pytest
Requires-Dist: opencv-python
Requires-Dist: rich
